qbt_rules/__init__.py
qbt_rules/__version__.py
qbt_rules/api.py
qbt_rules/arguments.py
qbt_rules/cli.py
qbt_rules/config.py
qbt_rules/engine.py
qbt_rules/errors.py
qbt_rules/logging.py
qbt_rules/py.typed
qbt_rules/utils.py
qbt_rules-0.3.2.dist-info/licenses/LICENSE
qbt_rules-0.3.2.dist-info/METADATA
qbt_rules-0.3.2.dist-info/WHEEL
qbt_rules-0.3.2.dist-info/entry_points.txt
qbt_rules-0.3.2.dist-info/top_level.txt
qbt_rules-0.3.2.dist-info/RECORD
