Metadata-Version: 2.4
Name: qbt-rules
Version: 0.3.2
Summary: A powerful Python-based rules engine for qBittorrent automation
Author: andronics
License: Unlicense
Project-URL: Homepage, https://github.com/andronics/qbt-rules
Project-URL: Documentation, https://github.com/andronics/qbt-rules/wiki
Project-URL: Repository, https://github.com/andronics/qbt-rules
Project-URL: Issues, https://github.com/andronics/qbt-rules/issues
Project-URL: Changelog, https://github.com/andronics/qbt-rules/blob/main/CHANGELOG.md
Keywords: qbittorrent,automation,torrent,rules-engine,api
Classifier: Development Status :: 4 - Beta
Classifier: Intended Audience :: End Users/Desktop
Classifier: License :: Public Domain
Classifier: Operating System :: OS Independent
Classifier: Programming Language :: Python :: 3
Classifier: Programming Language :: Python :: 3.8
Classifier: Programming Language :: Python :: 3.9
Classifier: Programming Language :: Python :: 3.10
Classifier: Programming Language :: Python :: 3.11
Classifier: Programming Language :: Python :: 3.12
Classifier: Topic :: Communications :: File Sharing
Classifier: Topic :: Utilities
Requires-Python: >=3.8
License-File: LICENSE
Requires-Dist: requests>=2.31.0
Requires-Dist: PyYAML>=6.0.2
Provides-Extra: dev
Requires-Dist: pytest>=7.4.0; extra == "dev"
Requires-Dist: pytest-cov>=4.1.0; extra == "dev"
Requires-Dist: mypy>=1.5.0; extra == "dev"
Requires-Dist: black>=23.7.0; extra == "dev"
Requires-Dist: ruff>=0.0.287; extra == "dev"
Requires-Dist: types-requests>=2.31.0; extra == "dev"
Requires-Dist: types-PyYAML>=6.0.12; extra == "dev"
Dynamic: license-file
